setup.py
TracNavPlus.egg-info/PKG-INFO
TracNavPlus.egg-info/SOURCES.txt
TracNavPlus.egg-info/dependency_links.txt
TracNavPlus.egg-info/entry_points.txt
TracNavPlus.egg-info/requires.txt
TracNavPlus.egg-info/top_level.txt
navplus/__init__.py
navplus/admin.py
navplus/filter.py
