Metadata-Version: 1.0
Name: TracNavPlus
Version: 1.0
Summary: Enhanced control over the navigation bars.
Home-page: http://trac-hacks.org/wiki/NavPlusPlugin
Author: Noah Kantrowitz
Author-email: coderanger@yahoo.com
License: BSD
Keywords: trac plugin
Platform: UNKNOWN
Classifier: Framework :: Trac
